Metadata-Version: 2.1
Name: py-rmq
Version: 0.0.5
Summary: Python ali rocketMQ api
Home-page: https://github.com/haifengat/py_rmq
Author: HaiFeng
Author-email: haifengat@vip.qq.com
License: MIT License
Platform: x64
Classifier: Programming Language :: Python :: 3
Classifier: Programming Language :: Python :: 3.6
Classifier: Programming Language :: Python :: 3.7
Classifier: License :: OSI Approved :: MIT License
Classifier: Operating System :: OS Independent
Requires-Python: >=3.6.0
